ask_crawling/crawling_news.py
ask_crawling/crawling_tweet.py
ask_crawling/path.py
ask_crawling/sentimentNews.py
ask_crawling-0.0.0.dist-info/LICENSE
ask_crawling-0.0.0.dist-info/METADATA
ask_crawling-0.0.0.dist-info/WHEEL
ask_crawling-0.0.0.dist-info/top_level.txt
ask_crawling-0.0.0.dist-info/RECORD
