Metadata-Version: 2.1
Name: ask-crawling
Version: 0.0.0
Summary: crawling package for A.S.K.
Home-page: https://github.com/DW-K/ask_crawling.git
Author: DW-K
Author-email: pch14545@gmail.com
License: MIT
Platform: UNKNOWN
Requires-Python: >=3.7
